<?xml version="1.0" encoding="UTF-8"?>
<!DOCTYPE mapper PUBLIC "-//mybatis.org//DTD Mapper 3.0//EN"
	"http://mybatis.org/dtd/mybatis-3-mapper.dtd">
	
<mapper namespace="com.ssafy.hotplace.model.mapper.HotplaceMapper">

	<!-- 2. resultMap 설정 -->
	<resultMap type="hotplaceDto" id="hotplace">
		<result column="hotplace_no" property="hotplaceNo"></result>
		<result column="user_no" property="userNo" />
		<result column="hotplace_name" property="hotplaceName" />
		<result column="hotplace_addr" property="hotplaceAddr" />
		<result column="category" property="category"/>
		<result column="hotplace_content" property="hotplaceContent" />
		<result column="jibun" property="jibun" />
		<result column="latitude" property="latitude" />
		<result column="longitude" property="longitude" />
	</resultMap>

	
	<!-- 핫플레이스 등록 -->
	<insert id="insert">
		insert into hotplace (user_no, hotplace_name, hotplace_addr, category, hotplace_content, jibun, latitude, longitude, img, org_img)
		values (#{userNo}, #{hotplaceName}, #{hotplaceAddr}, #{category}, #{hotplaceContent}, #{jibun}, #{latitude}, #{longitude}, #{img}, #{orgImg})
	</insert>
	
	<!-- 핫플레이스 전체 조회 -->
	<select id="selectAll" resultMap="hotplace">
		select *
		from hotplace;
	</select>
	
	<!-- 핫플레이스 검색 -->
	<select id="selectKeyword" parameterType="searchCondition" resultMap="hotplace">
		select *
		from hotplace
		<if test="key != 'none'">
			WHERE ${key} like concat('%', #{word}, '%')
		</if>
	</select>
	
	<!-- 핫플레이스 하나씩 조회 -->
	<select id="selectOne" resultMap="hotplace">
		SELECT *
		FROM hotplace
		WHERE hotplace_no = #{hotplaceNo}
	</select>

	<!-- 핫플레이스 글 삭제 -->
	<delete id="delete">
		DELETE
		FROM hotplace
		WHERE hotplace_no = #{hotplaceNo}
	</delete>
	
	<!-- 핫플레이스 좋아요 조회 -->
	<select id="countLike" resultType="_int">
		SELECT count(user_no)
		FROM hotplace_like
		WHERE hotplace_no = #{hotplaceNo}
	</select>
</mapper>

